nonebot_plugin_handle/__init__.py
nonebot_plugin_handle/config.py
nonebot_plugin_handle/data_source.py
nonebot_plugin_handle/resources/data/answers.json
nonebot_plugin_handle/resources/data/idioms.txt
nonebot_plugin_handle/resources/fonts/NotoSansMono-Regular.ttf
nonebot_plugin_handle/resources/fonts/NotoSerifSC-Regular.otf
nonebot_plugin_handle/utils.py
nonebot_plugin_handle-0.4.4.dist-info/LICENSE
nonebot_plugin_handle-0.4.4.dist-info/METADATA
nonebot_plugin_handle-0.4.4.dist-info/WHEEL
nonebot_plugin_handle-0.4.4.dist-info/RECORD
